AutoCleanPy/AutoDataClean.py
AutoCleanPy/__init__.py
AutoCleanPy-0.0.1.dist-info/LICENSE
AutoCleanPy-0.0.1.dist-info/METADATA
AutoCleanPy-0.0.1.dist-info/WHEEL
AutoCleanPy-0.0.1.dist-info/top_level.txt
AutoCleanPy-0.0.1.dist-info/RECORD
